wizsdk/__init__.py
wizsdk/battle.py
wizsdk/card.py
wizsdk/client.py
wizsdk/constants.py
wizsdk/hotkey.py
wizsdk/images/confirm.png
wizsdk/images/enemy-first.png
wizsdk/images/friendlist.png
wizsdk/images/spellbook.png
wizsdk/images/x.png
wizsdk/keyboard.py
wizsdk/mouse.py
wizsdk/pixels.py
wizsdk/utils.py
wizsdk/window.py
wizsdk-1.5.0.dist-info/LICENSE
wizsdk-1.5.0.dist-info/WHEEL
wizsdk-1.5.0.dist-info/METADATA
wizsdk-1.5.0.dist-info/RECORD
